{
    "nome": "Escola CEFCM",
    "tipo": "Instituição de Ensino Fundamental e Médio",
    "endereco": "R. Machado Bitencourt, s/n - Andaia, Santo Antônio de Jesus - BA, 44570-330",
    "contato": "(75) 3631-3502",
    "infraestrutura": "Laboratórios modernos, biblioteca, quadra esportiva e salas equipadas. Corpo docente qualificado e diversas atividades extracurriculares.",
    "projetos": "Projetos de inclusão digital, parcerias com instituições locais e programas de reforço escolar.",
    "diretora": "Joelma de Queiroz Nunes.",
    "coordenadas": [-12.9704024, -39.2702005]
  }
  